fakelish/__init__.py
fakelish/_scm_version.py
fakelish/console.py
fakelish/fakelish.py
fakelish/word-probability.json
fakelish-0.1.0.dist-info/LICENSE
fakelish-0.1.0.dist-info/METADATA
fakelish-0.1.0.dist-info/WHEEL
fakelish-0.1.0.dist-info/entry_points.txt
fakelish-0.1.0.dist-info/top_level.txt
fakelish-0.1.0.dist-info/RECORD
