Metadata-Version: 2.1
Name: fakelish
Version: 0.1.0
Summary: English-like word generator
Home-page: https://github.com/scrool/fakelish
Author: Pavol Babinčák
Author-email: scroolik@gmail.com
Maintainer: Pavol Babinčák
Maintainer-email: scroolik@gmail.com
License: MIT
Project-URL: Bug Tracker, https://github.com/scrool/fakelish/issues
Platform: Any
Classifier: Development Status :: 4 - Beta
Classifier: Environment :: Console
Classifier: Intended Audience :: End Users/Desktop
Classifier: License :: OSI Approved :: MIT License
Classifier: Natural Language :: English
Classifier: Operating System :: OS Independent
Classifier: Programming Language :: Python :: 3
Classifier: Programming Language :: Python :: 3 :: Only
Classifier: Programming Language :: Python :: 3.7
Classifier: Programming Language :: Python :: 3.8
Classifier: Programming Language :: Python :: 3.9
Classifier: Programming Language :: Python :: 3.10
Requires-Python: >=3.7
License-File: LICENSE
Provides-Extra: release
Requires-Dist: build ; extra == 'release'
Requires-Dist: twine ; extra == 'release'
Provides-Extra: test
Requires-Dist: pytest (>=6) ; extra == 'test'
Requires-Dist: tox ; extra == 'test'
